{
    "_via_settings": {
        "ui": {
            "annotation_editor_height": 25,
            "annotation_editor_fontsize": 0.8,
            "leftsidebar_width": 18,
            "image_grid": {
                "img_height": 80,
                "rshape_fill": "none",
                "rshape_fill_opacity": 0.3,
                "rshape_stroke": "yellow",
                "rshape_stroke_width": 2,
                "show_region_shape": true,
                "show_image_policy": "all"
            },
            "image": {
                "region_label": "",
                "region_label_font": "10px Sans",
                "on_image_annotation_editor_placement": "NEAR_REGION"
            }
        },
        "core": {
            "buffer_size": "18",
            "filepath": {
                "/mrcnn4/": 3
            },
            "default_filepath": "./data"
        },
        "project": {
            "name": "via_data_end"
        }
    },
    "_via_img_metadata": {
        "250031471orig.jpeg": {
            "file_attributes": {},
            "filename": "250031471orig.jpeg",
            "regions": [
                {
                    "region_attributes": {
                        "class": "numberplate",
                        "region_name": "eu",
                        "np": "NEBV043"
                    },
                    "shape_attributes": {
                        "name": "polygon",
                        "all_points_x": [
                            482,
                            522,
                            291,
                            261
                        ],
                        "all_points_y": [
                            695,
                            767,
                            903,
                            842
                        ]
                    }
                }
            ],
            "size": 0
        }
    },
    "_via_attributes": {
        "region": {
            "class": {
                "type": "text"
            }
        },
        "file": {}
    }
}
